{
  "project_info": {
    "project_number": "1026744307792",
    "firebase_url": "https://leanplumtse.firebaseio.com",
    "project_id": "leanplumtse",
    "storage_bucket": "leanplumtse.appspot.com"
  },
  "client": [
    {
      "client_info": {
        "mobilesdk_app_id": "1:1026744307792:android:66e06327498a61d6",
        "android_client_info": {
          "package_name": "com.android_playground"
        }
      },
      "oauth_client": [
        {
          "client_id": "1026744307792-h5i5ofduopkb1o3lt0jintmhksqdqvje.apps.googleusercontent.com",
          "client_type": 3
        },
        {
          "client_id": "1026744307792-h5i5ofduopkb1o3lt0jintmhksqdqvje.apps.googleusercontent.com",
          "client_type": 3
        }
      ],
      "api_key": [
        {
          "current_key": "AIzaSyDPxyuTLhUe77Z7-o0YnecA9Pmr5EqzFgE"
        }
      ],
      "services": {
        "analytics_service": {
          "status": 1
        },
        "appinvite_service": {
          "status": 1,
          "other_platform_oauth_client": []
        },
        "ads_service": {
          "status": 2
        }
      }
    },
    {
      "client_info": {
        "mobilesdk_app_id": "1:1026744307792:android:c1a90189283d5eab",
        "android_client_info": {
          "package_name": "com.lp.android_mparticle_lp"
        }
      },
      "oauth_client": [
        {
          "client_id": "1026744307792-h5i5ofduopkb1o3lt0jintmhksqdqvje.apps.googleusercontent.com",
          "client_type": 3
        },
        {
          "client_id": "1026744307792-h5i5ofduopkb1o3lt0jintmhksqdqvje.apps.googleusercontent.com",
          "client_type": 3
        }
      ],
      "api_key": [
        {
          "current_key": "AIzaSyDPxyuTLhUe77Z7-o0YnecA9Pmr5EqzFgE"
        }
      ],
      "services": {
        "analytics_service": {
          "status": 1
        },
        "appinvite_service": {
          "status": 1,
          "other_platform_oauth_client": []
        },
        "ads_service": {
          "status": 2
        }
      }
    }
  ],
  "configuration_version": "1"
}